eNlightSDK/__init__.py
eNlightSDK/enlight_cloud.py
eNlightSDK/classes/__init__.py
eNlightSDK/classes/caller.py
eNlightSDK/classes/set_projects.py
eNlightSDK/classes/vm.py
CloudVmDemo-4.0.dist-info/METADATA
CloudVmDemo-4.0.dist-info/WHEEL
CloudVmDemo-4.0.dist-info/top_level.txt
CloudVmDemo-4.0.dist-info/RECORD
