Metadata-Version: 2.1
Name: CloudVmDemo
Version: 4.0
Summary: eNlight Cloud VM create, update, retrive, delete and VM actions
Author: Akshay Ghatol
Author-email: akshay.ghatol@esds.co.in
Requires-Dist: requests
